{
    "wallpaper": "/usr/share/backgrounds/looplinux-wallpaper-v2/5.jpg",
    "alpha": "100",
    "special": {
        "background": "#010102",
        "foreground": "#96d8ed",
        "cursor": "#96d8ed"
    },
    "colors": {
        "color0": "#010102",
        "color1": "#D5CF13",
        "color2": "#032694",
        "color3": "#0757A5",
        "color4": "#115BD0",
        "color5": "#D53CB6",
        "color6": "#0C9DF3",
        "color7": "#96d8ed",
        "color8": "#6997a5",
        "color9": "#D5CF13",
        "color10": "#032694",
        "color11": "#0757A5",
        "color12": "#115BD0",
        "color13": "#D53CB6",
        "color14": "#0C9DF3",
        "color15": "#96d8ed"
    }
}